vtypes/__init__.py
vtypes/_version.py
vtypes/core.py
vtypes/py.typed
vtypes-0.5.1.dist-info/LICENSE
vtypes-0.5.1.dist-info/METADATA
vtypes-0.5.1.dist-info/WHEEL
vtypes-0.5.1.dist-info/top_level.txt
vtypes-0.5.1.dist-info/RECORD
