Metadata-Version: 2.1
Name: vtypes
Version: 0.5.1
Summary: Validating Types: use `isinstance()` to validate both type and value.
Home-page: https://github.com/smarie/python-vtypes
Maintainer: Sylvain Marié
Maintainer-email: sylvain.marie@se.com
License: BSD 3-Clause
Download-URL: https://github.com/smarie/python-vtypes/tarball/0.5.1
Keywords: type class instance value valid validate validator validation check checker checking
Platform: UNKNOWN
Classifier: Development Status :: 5 - Production/Stable
Classifier: Intended Audience :: Developers
Classifier: Topic :: Software Development :: Libraries :: Python Modules
Classifier: License :: OSI Approved :: BSD License
Classifier: Programming Language :: Python :: 2.7
Classifier: Programming Language :: Python :: 3.5
Classifier: Programming Language :: Python :: 3.6
Classifier: Programming Language :: Python :: 3.7
Requires-Dist: six
Requires-Dist: valid8
